setup.cfg
setup.py
pyf/__init__.py
pyf.componentized.egg-info/PKG-INFO
pyf.componentized.egg-info/SOURCES.txt
pyf.componentized.egg-info/dependency_links.txt
pyf.componentized.egg-info/entry_points.txt
pyf.componentized.egg-info/namespace_packages.txt
pyf.componentized.egg-info/not-zip-safe
pyf.componentized.egg-info/requires.txt
pyf.componentized.egg-info/top_level.txt
pyf/componentized/__init__.py
pyf/componentized/builtins/__init__.py
pyf/componentized/builtins/joiners.py
pyf/componentized/components/__init__.py
pyf/componentized/components/adapter.py
pyf/componentized/components/base.py
pyf/componentized/components/config.py
pyf/componentized/components/configuration.py
pyf/componentized/components/joiner.py
pyf/componentized/components/managed.py
pyf/componentized/components/multiwriter.py
pyf/componentized/components/producer.py
pyf/componentized/components/resource.py
pyf/componentized/components/writer.py
pyf/componentized/configuration/__init__.py
pyf/componentized/configuration/fields.py
pyf/componentized/configuration/keys.py
pyf/componentized/core/__init__.py
pyf/componentized/core/manager.py
pyf/componentized/error/__init__.py
pyf/componentized/error/manager.py
pyf/componentized/error/writer.py