Metadata-Version: 1.0
Name: pyf.componentized
Version: 2.0.3
Summary: Component system for flow based programming with XML configuration system.
Home-page: http://pyfproject.org
Author: htaieb,  jonathan schemoul
Author-email: he.taieb@gmail.com, jonathan.schemoul@gmail.com
License: MIT
Keywords: flow pyf zflow programming plugins components
Platform: UNKNOWN
